sm_4rel4in/__init__.py
sm_4rel4in-1.0.6.dist-info/LICENSE
sm_4rel4in-1.0.6.dist-info/METADATA
sm_4rel4in-1.0.6.dist-info/WHEEL
sm_4rel4in-1.0.6.dist-info/top_level.txt
sm_4rel4in-1.0.6.dist-info/RECORD
