Metadata-Version: 2.1
Name: sm-4rel4in
Version: 1.0.6
Summary: Library for Sequent Microsystems Four Relays four HV Inputs 8-Layer Stackable HAT for Raspberry Pi
Home-page: https://sequentmicrosystems.com
Author: Sequent Microsystems
Author-email: olcitu@gmail.com
License: MIT
Keywords: industrial,raspberry,power,optoisolated,relay,pulse count,pwm read,quadrature encoders,frequency read,digital input,AC/DC input
Classifier: Development Status :: 4 - Beta
Classifier: Intended Audience :: Developers
Classifier: Topic :: Software Development :: Build Tools
Classifier: License :: OSI Approved :: MIT License
Classifier: Programming Language :: Python :: 2.7
Classifier: Programming Language :: Python :: 3
Classifier: Programming Language :: Python :: 3.4
Classifier: Programming Language :: Python :: 3.5
Classifier: Programming Language :: Python :: 3.6
Classifier: Programming Language :: Python :: 3.7
License-File: LICENSE
Requires-Dist: smbus2
